wscls/__init__.py
wscls/wscls.py
wscls-1.1.9.dist-info/LICENSE
wscls-1.1.9.dist-info/METADATA
wscls-1.1.9.dist-info/WHEEL
wscls-1.1.9.dist-info/entry_points.txt
wscls-1.1.9.dist-info/top_level.txt
wscls-1.1.9.dist-info/RECORD
