Metadata-Version: 2.1
Name: wscls
Version: 1.1.9
Summary: Websocket terminal client
Author: Maksim Nikitenko
Author-email: iam@sets88.com
License: BSD
Platform: any
Requires-Python: >=3.9
License-File: LICENSE
Requires-Dist: textual==0.82.0
Requires-Dist: aiohttp==3.9.3
Requires-Dist: pyperclip==1.9.0
